{"City": "Asuncion", "District": "NULL", "Headline": "Lìderes campesinos protestan contra presidente Cartes en marcha en Asunción", "Source": "Factiva", "Target Sectors": "Elite,Executive,Executive Office,Government", "Province": "Asuncion", "Source Sectors": "Labor,Social", "Event Date": "2015-03-26", "Event ID": "24015796", "Publisher": "Agence France-Presse", "Country": "Paraguay", "Source Country": "Paraguay", "Story ID": "36967504", "Target Country": "Paraguay", "Longitude": "-57.6359", "Event Sentence": "Some 3,000 landless workers of the organization National Campesino Federation (FNC) staged a protest against the government of president Horacio Cartes this Thursday in the Paraguayan capital, observed a journalist of the AFP.", "Event Text": "Demonstrate or rally", "Sentence Number": "1", "embersId": "a0ddb9daa9c81af4cabbb87d3806e4d441f3a895", "Latitude": "-25.3007", "Target Name": "Horacio Cartes", "Source Name": "Employee (Paraguay)", "Intensity": "-6.5"}
